dab_py-1.1.0.dist-info/licenses/LICENSE
dabpy/__init__.py
dabpy/constraints.py
dabpy/dab_py.py
dabpy/om_api.py
dab_py-1.1.0.dist-info/.gitignore
dab_py-1.1.0.dist-info/METADATA
dab_py-1.1.0.dist-info/WHEEL
dab_py-1.1.0.dist-info/top_level.txt
dab_py-1.1.0.dist-info/RECORD
