Metadata-Version: 2.4
Name: dab_py
Version: 1.1.0
Summary: A Python client for DAB Terms API and DAB API (WHOS / HIS-Central API)
Home-page: https://github.com/ESSI-Lab/dab-py/tree/main
Author: Alun Sagara Putra (CNR Internship)
License: AGPL-3.0
Classifier: Programming Language :: Python :: 3
Classifier: License :: OSI Approved :: GNU Affero General Public License v3
Classifier: Operating System :: OS Independent
Requires-Python: >=3.7
License-File: LICENSE
Requires-Dist: requests
Requires-Dist: pandas
Requires-Dist: matplotlib
Dynamic: author
Dynamic: classifier
Dynamic: description
Dynamic: description-content-type
Dynamic: home-page
Dynamic: license
Dynamic: license-file
Dynamic: requires-dist
Dynamic: requires-python
Dynamic: summary
